eu/__init__.py
eu/softfire/__init__.py
eu/softfire/sec/Api.py
eu/softfire/sec/SecurityManager.py
eu/softfire/sec/__init__.py
eu/softfire/sec/exceptions/__init__.py
eu/softfire/sec/exceptions/exceptions.py
eu/softfire/sec/utils/OBclient.py
eu/softfire/sec/utils/OSclient.py
eu/softfire/sec/utils/__init__.py
eu/softfire/sec/utils/fauxapi_lib.py
eu/softfire/sec/utils/pfsense_utils.py
eu/softfire/sec/utils/utils.py
security_manager-0.2.7.data/scripts/security-manager
security_manager-0.2.7.dist-info/DESCRIPTION.rst
security_manager-0.2.7.dist-info/METADATA
security_manager-0.2.7.dist-info/RECORD
security_manager-0.2.7.dist-info/WHEEL
security_manager-0.2.7.dist-info/metadata.json
security_manager-0.2.7.dist-info/top_level.txt
