Metadata-Version: 2.0
Name: security-manager
Version: 0.2.7
Summary: The SoftFIRE Security Manager
Home-page: https://github.com/softfire-eu/security-manager
Author: SoftFIRE
Author-email: softfire@softfire.eu
License: Apache 2
Keywords: python vnfm nfvo open baton openbaton sdk experiment manager softfire tosca openstack rest security firewall ips
Platform: UNKNOWN
Classifier: Development Status :: 4 - Beta
Classifier: Intended Audience :: Developers
Classifier: License :: OSI Approved :: Apache Software License
Requires-Dist: bcrypt
Requires-Dist: bottle
Requires-Dist: IPy
Requires-Dist: keystoneauth
Requires-Dist: python-neutronclient
Requires-Dist: python-novaclient
Requires-Dist: python-glanceclient
Requires-Dist: openbaton-cli (==5.0.1)
Requires-Dist: python-neutronclient
Requires-Dist: PyYAML
Requires-Dist: requests
Requires-Dist: softfire-sdk (==1.1.4)
Requires-Dist: beaker
Requires-Dist: paramiko
Requires-Dist: scp
Requires-Dist: idstools
Requires-Dist: pexpect
